py7zr/__init__.py
py7zr/__main__.py
py7zr/archiveinfo.py
py7zr/callbacks.py
py7zr/cli.py
py7zr/compressor.py
py7zr/exceptions.py
py7zr/helpers.py
py7zr/io.py
py7zr/member.py
py7zr/properties.py
py7zr/py.typed
py7zr/py7zr.py
py7zr/version.py
py7zr/win32compat.py
py7zr-1.1.2.dist-info/licenses/LICENSE
py7zr-1.1.2.dist-info/METADATA
py7zr-1.1.2.dist-info/WHEEL
py7zr-1.1.2.dist-info/entry_points.txt
py7zr-1.1.2.dist-info/top_level.txt
py7zr-1.1.2.dist-info/RECORD
