Metadata-Version: 2.4
Name: py7zr
Version: 1.1.2
Summary: Pure python 7-zip library
Author-email: Hiroshi Miura <miurahr@linux.com>
License-Expression: LGPL-2.1-or-later
Project-URL: Homepage, https://py7zr.readthedocs.io/
Project-URL: Documentation, https://py7zr.readthedocs.io/en/stable/
Project-URL: Bug Tracker, https://github.com/miurahr/py7zr/issues
Project-URL: Source, https://github.com/miurahr/py7zr
Project-URL: Changelog, https://py7zr.readthedocs.io/en/latest/Changelog.html
Keywords: compression,7zip,lzma,zstandard,ppmd,lzma2,bcj,archive
Classifier: Development Status :: 5 - Production/Stable
Classifier: Operating System :: MacOS :: MacOS X
Classifier: Operating System :: Microsoft :: Windows
Classifier: Operating System :: POSIX
Classifier: Operating System :: POSIX :: Linux
Classifier: Programming Language :: Python
Classifier: Programming Language :: Python :: 3
Classifier: Programming Language :: Python :: 3.10
Classifier: Programming Language :: Python :: 3.11
Classifier: Programming Language :: Python :: 3.12
Classifier: Programming Language :: Python :: 3.13
Classifier: Programming Language :: Python :: 3.14
Classifier: Programming Language :: Python :: 3 :: Only
Classifier: Programming Language :: Python :: Implementation :: CPython
Classifier: Programming Language :: Python :: Implementation :: PyPy
Classifier: Topic :: Software Development :: Libraries :: Python Modules
Requires-Python: >=3.10
License-File: LICENSE
Requires-Dist: texttable
Requires-Dist: pycryptodomex>=3.20.0
Requires-Dist: brotli>=1.2.0; platform_python_implementation == "CPython"
Requires-Dist: brotlicffi>=1.2.0.0; platform_python_implementation == "PyPy"
Requires-Dist: psutil; sys_platform != "cygwin"
Requires-Dist: backports.zstd>=1.0.0; python_version < "3.14"
Requires-Dist: pyppmd>=1.3.1
Requires-Dist: pybcj>=1.0.6
Requires-Dist: multivolumefile>=0.2.3
Requires-Dist: inflate64>=1.0.4
Provides-Extra: test
Requires-Dist: pytest; extra == "test"
Requires-Dist: pytest-benchmark; extra == "test"
Requires-Dist: pytest-cov; extra == "test"
Requires-Dist: pytest-remotedata; extra == "test"
Requires-Dist: pytest-timeout; extra == "test"
Requires-Dist: py-cpuinfo; extra == "test"
Requires-Dist: coverage[toml]>=7.10.7; extra == "test"
Requires-Dist: coveralls>=4.0.2; extra == "test"
Requires-Dist: requests; extra == "test"
Requires-Dist: pytest-httpserver; extra == "test"
Provides-Extra: docs
Requires-Dist: sphinx>=8.0.0; extra == "docs"
Requires-Dist: sphinx-py3doc-enhanced-theme; extra == "docs"
Requires-Dist: sphinx-a4doc; extra == "docs"
Requires-Dist: docutils; extra == "docs"
Provides-Extra: check
Requires-Dist: mypy>=1.17.0; extra == "check"
Requires-Dist: mypy_extensions>=1.1.0; extra == "check"
Requires-Dist: lxml; extra == "check"
Requires-Dist: types-psutil; extra == "check"
Requires-Dist: check-manifest; extra == "check"
Requires-Dist: flake8<8; extra == "check"
Requires-Dist: flake8-black>=0.3.6; extra == "check"
Requires-Dist: flake8-deprecated; extra == "check"
Requires-Dist: flake8-isort; extra == "check"
Requires-Dist: isort>=7.0.0; extra == "check"
Requires-Dist: pygments; extra == "check"
Requires-Dist: readme-renderer; extra == "check"
Requires-Dist: twine; extra == "check"
Requires-Dist: black>=25.1.0; extra == "check"
Requires-Dist: pylint; extra == "check"
Provides-Extra: debug
Requires-Dist: pytest; extra == "debug"
Requires-Dist: pytest-leaks; extra == "debug"
Requires-Dist: pytest-profiling; extra == "debug"
Dynamic: license-file
